getdatatestbed/__init__.py
getdatatestbed/download_grid_data.py
getdatatestbed/getDataFRF.py
getdatatestbed/getOutsideData.py
getdatatestbed/getPlotData.py
getdatatestbed/setup.py
getdatatestbed-0.1.4.dist-info/METADATA
getdatatestbed-0.1.4.dist-info/WHEEL
getdatatestbed-0.1.4.dist-info/top_level.txt
getdatatestbed-0.1.4.dist-info/RECORD
